pccloner/__init__.py
pccloner/pcdata.py
pccloner/pctask_pr.py
pccloner/pctask_press.py
pccloner/ubuntu.py
pccloner/utils.py
pccloner/win11.py
pccloner-0.1.8.dist-info/LICENSE
pccloner-0.1.8.dist-info/METADATA
pccloner-0.1.8.dist-info/WHEEL
pccloner-0.1.8.dist-info/top_level.txt
pccloner-0.1.8.dist-info/RECORD
