Metadata-Version: 2.1
Name: pccloner
Version: 0.1.8
Summary: Clone your repetitive PC tasks
Home-page: https://github.com/ezamorag/pccloner
Author: Erik Zamora
Author-email: ezamora1981@gmail.com
Classifier: Programming Language :: Python :: 3
Classifier: License :: OSI Approved :: MIT License
Classifier: Operating System :: OS Independent
Requires-Python: >=3.10
License-File: LICENSE
Requires-Dist: pynput >=1.7.6
Requires-Dist: pyautogui >=0.9.54
Requires-Dist: keyboard >=0.13.5
Requires-Dist: pandas >=2.1.4
Requires-Dist: py7zr >=0.22.0
Requires-Dist: mss >=9.0.2
